zorg_firmata-0.0.4.dist-info/RECORD
zorg_firmata-0.0.4.dist-info/top_level.txt
zorg_firmata-0.0.4.dist-info/metadata.json
zorg_firmata-0.0.4.dist-info/zip-safe
zorg_firmata-0.0.4.dist-info/METADATA
zorg_firmata-0.0.4.dist-info/DESCRIPTION.rst
zorg_firmata-0.0.4.dist-info/WHEEL
tests/__init__.py
tests/test_adaptor.py
zorg_firmata/adaptor.py
zorg_firmata/__init__.py
